tetanes_py-0.1.9.dist-info/METADATA
tetanes_py-0.1.9.dist-info/WHEEL
tetanes_py/__init__.py
tetanes_py/_tetanes.abi3.so
tetanes_py/py.typed
tetanes_py-0.1.9.dist-info/RECORD
