Metadata-Version: 2.4
Name: tetanes-py
Version: 0.1.9
Classifier: Development Status :: 3 - Alpha
Classifier: Intended Audience :: Developers
Classifier: Intended Audience :: Science/Research
Classifier: License :: OSI Approved :: MIT License
Classifier: License :: OSI Approved :: Apache Software License
Classifier: Programming Language :: Python :: 3
Classifier: Programming Language :: Python :: 3.8
Classifier: Programming Language :: Python :: 3.9
Classifier: Programming Language :: Python :: 3.10
Classifier: Programming Language :: Python :: 3.11
Classifier: Programming Language :: Python :: 3.12
Classifier: Programming Language :: Rust
Classifier: Topic :: Scientific/Engineering :: Artificial Intelligence
Classifier: Topic :: Games/Entertainment
Classifier: Topic :: Software Development :: Libraries :: Python Modules
Requires-Dist: numpy>=1.20.0
Requires-Dist: gymnasium>=0.26.0
Provides-Extra: dev
Provides-Extra: examples
Summary: TetaNES-Py - Python bindings for the TetaNES NES emulator with Gymnasium support
Home-Page: https://lukeworks.tech/tetanes
Author-email: Alexei Quick <alexei.quick@gmail.com>
License: MIT OR Apache-2.0
Requires-Python: >=3.8
